[
  {
    "id": "580e0af8-40d0-4418-993e-8ed2403a111a",
    "title": "Track 1 Allotment",
    "description": "test",
    "pdfUrl": null,
    "createdAt": "2026-03-18T13:51:46.379Z",
    "updatedAt": "2026-03-20T05:44:33.399Z",
    "tableData": {
      "headers": [
        "Index",
        "Name of the event",
        "Registration Desk",
        "Faculty Coordinators",
        "Students Coordinators",
        "Start",
        "End",
        "Room No."
      ],
      "rows": [
        [
          "1",
          "Competition Project Review",
          "",
          "Dr. Gauri Sahoo",
          "\"Vineet",
          "Saish\"",
          "12:30 PM",
          "2:00 PM",
          "205"
        ],
        [
          "2",
          "Competition Project Review",
          "",
          "Dr. Gauri Sahoo",
          "Srushti",
          "12:30 PM",
          "2:00 PM",
          "206"
        ],
        [
          "3",
          "Line Following bots Game",
          "Janhavi",
          "Prasanna",
          "Mr. Abhijit Shete",
          "Ritika",
          "12:40 PM",
          "2:00 PM",
          "Amphitheatre"
        ],
        [
          "4",
          "Treasure Hunt",
          "Idhant",
          "Shantanu",
          "Mrs. Amrita Jhaveri",
          "\"Sneha",
          "Anushka",
          "Purvi\"",
          "12:45 PM",
          "2:00 PM",
          "\"214 & 215\""
        ],
        [
          "5",
          "Robotic arm Games",
          "",
          "Mr. Abhijit Shete",
          "\"Aayan",
          "Atharva",
          "Prajwal\"",
          "12:40 PM",
          "2:00 PM",
          "201"
        ],
        [
          "6",
          "Hardware Project Exhibition",
          "",
          "Dr. Jaymala Adsul",
          "\"Riddhi",
          "Maitreyy\"",
          "12:40 PM",
          "2:00 PM",
          "201"
        ],
        [
          "7",
          "Arrangements &",
          "Kalpesh",
          "Dhruv",
          "Shantanu",
          "Mrs. Sneha Sapre",
          "\"Vineet",
          "Prajwal",
          "Srushti\"",
          "1:30 PM",
          "",
          "Auditorium"
        ],
        [
          "8",
          "Refreshments",
          "",
          "Dr. Asawari Dudwadkar",
          "\"Ritika",
          "Riddhi\"",
          "12:00 PM",
          "12:30 PM",
          "204"
        ],
        [
          "9",
          "Attendance & Report",
          "",
          "",
          "\"Ritika",
          "Aastha\"",
          "",
          "",
          ""
        ],
        [
          "10",
          "Certificates",
          "",
          "Mrs. Amrita Jhaveri",
          "\"Purvi & Srushti\"",
          "",
          "",
          ""
        ],
        [
          "11",
          "Momento & certificates",
          "",
          "Mrs. Sarika Kuhikar",
          "Prajwal",
          "",
          "",
          ""
        ]
      ]
    }
  }
]